StatM/Base_class.py
StatM/Bisection.py
StatM/Regula_Falsi.py
StatM/Secant.py
StatM/__init__.py
StatM-0.1.4.dist-info/METADATA
StatM-0.1.4.dist-info/WHEEL
StatM-0.1.4.dist-info/top_level.txt
StatM-0.1.4.dist-info/RECORD
