Metadata-Version: 2.1
Name: StatM
Version: 0.1.4
Summary: This package implements 3 key Numerical Analysis iterative algorithms
Home-page: https://github.com/Blaizzy/Boring_weekends/tree/master/statistics
Author: Prince Canuma
Author-email: prince.gdt@gmail.com
License: UNKNOWN
Platform: UNKNOWN
Classifier: Programming Language :: Python :: 3
Classifier: License :: OSI Approved :: MIT License
Classifier: Operating System :: OS Independent
Classifier: Development Status :: 4 - Beta
